{
  "address": "Flat B 105, Evershot Road, London, N4 3DF",
  "postcode": "N4 3DF",
  "details": {
    "address": "Flat B 105, Evershot Road, London, N4 3DF",
    "licence_number": "ISL-930010019375",
    "licence_type": "Additional HMO licence",
    "year_built": "Pre 1919",
    "property_description": "Flat in multiple occupation",
    "licence_holder_name": "Mollie Giannakaki",
    "licence_holder_address": "25 Carysfort Road , London, N8 8RA",
    "uprn": "5300032161",
    "licence_start_date": "04/04/2023",
    "licence_end_date": "03/04/2028",
    "additional_details": {
      "no_of_storeys": "2",
      "sleeping_accommodation": "3",
      "living_accommodation": "1",
      "no_of_non_self_contained_flats_if_the_property_is_a_licensed_hmo_consisting_of_flats_(otherwise,_this_shows_no_of_bedrooms)": "3",
      "kitchens": "1",
      "bathrooms": "2",
      "maximum_permitted_occupants": "3",
      "maximum_permitted_households": "3"
    }
  },
  "scraped_at": "2026-06-26T20:39:59.494401"
}