{
  "address": "Flat 2 143, Mildmay Road, London, N1 4PT",
  "postcode": "N1 4PT",
  "details": {
    "address": "Flat 2 143, Mildmay Road, London, N1 4PT",
    "licence_number": "ISL-204640-1",
    "licence_type": "Mandatory HMO licence",
    "year_built": "Pre 1919",
    "property_description": "Flat in multiple occupation",
    "licence_holder_name": "Priory Pub Company Limited (David Gay)",
    "licence_holder_address": "3 Moreton Place , Harpenden, AL5 2UF",
    "uprn": "10090550993",
    "licence_start_date": "13/03/2023",
    "licence_end_date": "12/03/2028",
    "additional_details": {
      "no_of_storeys": "2",
      "sleeping_accommodation": "6",
      "living_accommodation": "1",
      "no_of_non_self_contained_flats_if_the_property_is_a_licensed_hmo_consisting_of_flats_(otherwise,_this_shows_no_of_bedrooms)": "6",
      "kitchens": "1",
      "bathrooms": "1",
      "maximum_permitted_occupants": "6",
      "maximum_permitted_households": "6"
    }
  },
  "scraped_at": "2026-05-07T05:18:07.103254"
}