{
  "source": "rightmove",
  "scraped_at": "2025-11-26T00:04:02.274332+00:00",
  "postcode": "N7 7QP",
  "id": 159676043,
  "bedrooms": 2,
  "bathrooms": 3,
  "numberOfImages": 12,
  "numberOfFloorplans": 1,
  "numberOfVirtualTours": 0,
  "summary": "Modern two-bedroom duplex apartment on Seven Sisters Road, spanning ground and lower-ground floors with a private patio. Features include a fitted kitchen, reception room, WC (all on the ground floor), two double bedrooms (one en-suite), and a family bathroom (on the lower ground floor). Close to...",
  "displayAddress": "Seven Sisters Road, London, N7 7QP",
  "countryCode": "GB",
  "location": {
    "latitude": 51.560148,
    "longitude": -0.115139
  },
  "images": [
    {
      "srcUrl": "https://media.rightmove.co.uk:443/dir/crop/10:9-16:9/257k/256541/159676043/256541_ARU-778231_IMG_00_0000_max_476x317.jpeg",
      "url": "257k/256541/159676043/256541_ARU-778231_IMG_00_0000.jpeg",
      "caption": null
    },
    {
      "srcUrl": "https://media.rightmove.co.uk:443/dir/crop/10:9-16:9/257k/256541/159676043/256541_ARU-778231_IMG_01_0000_max_476x317.jpeg",
      "url": "257k/256541/159676043/256541_ARU-778231_IMG_01_0000.jpeg",
      "caption": null
    },
    {
      "srcUrl": "https://media.rightmove.co.uk:443/dir/crop/10:9-16:9/257k/256541/159676043/256541_ARU-778231_IMG_02_0000_max_476x317.jpeg",
      "url": "257k/256541/159676043/256541_ARU-778231_IMG_02_0000.jpeg",
      "caption": null
    },
    {
      "srcUrl": "https://media.rightmove.co.uk:443/dir/crop/10:9-16:9/257k/256541/159676043/256541_ARU-778231_IMG_03_0000_max_476x317.jpeg",
      "url": "257k/256541/159676043/256541_ARU-778231_IMG_03_0000.jpeg",
      "caption": null
    },
    {
      "srcUrl": "https://media.rightmove.co.uk:443/dir/crop/10:9-16:9/257k/256541/159676043/256541_ARU-778231_IMG_04_0000_max_476x317.jpeg",
      "url": "257k/256541/159676043/256541_ARU-778231_IMG_04_0000.jpeg",
      "caption": null
    },
    {
      "srcUrl": "https://media.rightmove.co.uk:443/dir/crop/10:9-16:9/257k/256541/159676043/256541_ARU-778231_IMG_05_0000_max_476x317.jpeg",
      "url": "257k/256541/159676043/256541_ARU-778231_IMG_05_0000.jpeg",
      "caption": null
    },
    {
      "srcUrl": "https://media.rightmove.co.uk:443/dir/crop/10:9-16:9/257k/256541/159676043/256541_ARU-778231_IMG_06_0000_max_476x317.jpeg",
      "url": "257k/256541/159676043/256541_ARU-778231_IMG_06_0000.jpeg",
      "caption": null
    },
    {
      "srcUrl": "https://media.rightmove.co.uk:443/dir/crop/10:9-16:9/257k/256541/159676043/256541_ARU-778231_IMG_07_0000_max_476x317.jpeg",
      "url": "257k/256541/159676043/256541_ARU-778231_IMG_07_0000.jpeg",
      "caption": null
    },
    {
      "srcUrl": "https://media.rightmove.co.uk:443/dir/crop/10:9-16:9/257k/256541/159676043/256541_ARU-778231_IMG_08_0000_max_476x317.jpeg",
      "url": "257k/256541/159676043/256541_ARU-778231_IMG_08_0000.jpeg",
      "caption": null
    },
    {
      "srcUrl": "https://media.rightmove.co.uk:443/dir/crop/10:9-16:9/257k/256541/159676043/256541_ARU-778231_IMG_09_0000_max_476x317.jpeg",
      "url": "257k/256541/159676043/256541_ARU-778231_IMG_09_0000.jpeg",
      "caption": null
    },
    {
      "srcUrl": "https://media.rightmove.co.uk:443/dir/crop/10:9-16:9/257k/256541/159676043/256541_ARU-778231_IMG_10_0000_max_476x317.jpeg",
      "url": "257k/256541/159676043/256541_ARU-778231_IMG_10_0000.jpeg",
      "caption": null
    },
    {
      "srcUrl": "https://media.rightmove.co.uk:443/dir/crop/10:9-16:9/257k/256541/159676043/256541_ARU-778231_IMG_11_0000_max_476x317.jpeg",
      "url": "257k/256541/159676043/256541_ARU-778231_IMG_11_0000.jpeg",
      "caption": null
    }
  ],
  "propertySubType": "Flat",
  "tenure": {
    "tenureType": null
  },
  "letAvailableDate": "2025-03-20T00:00:00Z",
  "listingUpdate": {
    "listingUpdateReason": "price_reduced",
    "listingUpdateDate": "2025-10-06T11:17:56Z"
  },
  "price": {
    "amount": 2345,
    "frequency": "monthly",
    "currencyCode": "GBP",
    "displayPrices": [
      {
        "displayPrice": "\u00a32,345 pcm",
        "displayPriceQualifier": ""
      },
      {
        "displayPrice": "\u00a3541 pw",
        "displayPriceQualifier": ""
      }
    ]
  },
  "premiumListing": false,
  "featuredProperty": false,
  "commercialSearchProminenceSelected": false,
  "customer": {
    "branchId": 256541,
    "brandPlusLogoURI": "/257k/256541/branch_rmchoice_logo_256541_0001.png",
    "contactTelephone": "020 4530 8274",
    "branchDisplayName": "Woodfell, London",
    "branchName": "London",
    "brandTradingName": "Woodfell",
    "branchLandingPageUrl": "/estate-agents/agent/Woodfell/London-256541.html",
    "development": false,
    "mediaServerUrl": "https://media.rightmove.co.uk:443",
    "showReducedProperties": true,
    "hasBrandPlus": true,
    "commercial": false,
    "showOnMap": true,
    "enhancedListing": false,
    "developmentContent": null,
    "buildToRent": false,
    "buildToRentBenefits": [],
    "updateDate": "2025-11-25T15:45:10Z",
    "brandPlusLogoUrl": "https://media.rightmove.co.uk:443/257k/256541/branch_rmchoice_logo_256541_0001.png",
    "primaryBrandColour": null
  },
  "distance": null,
  "transactionType": "rent",
  "productLabel": {
    "productLabelText": null,
    "spotlightLabel": false
  },
  "commercial": false,
  "development": false,
  "residential": true,
  "students": false,
  "auction": false,
  "feesApply": true,
  "feesApplyText": null,
  "displaySize": "753 sq. ft.",
  "showOnMap": true,
  "propertyUrl": "/properties/159676043#/?channel=RES_LET",
  "contactUrl": "/property-to-rent/contactBranch.html?propertyId=159676043",
  "staticMapUrl": null,
  "channel": "RENT",
  "firstVisibleDate": "2025-03-20T15:30:30Z",
  "keywords": [],
  "tags": [],
  "keywordMatchType": "no_keyword",
  "saved": false,
  "hidden": false,
  "onlineViewingsAvailable": false,
  "lozengeModel": {
    "matchingLozenges": []
  },
  "streetView": {
    "showStreetView": true
  },
  "enquiredTimestamp": null,
  "updateDate": "2025-11-25T15:45:10Z",
  "enquiryAddedTimestamp": null,
  "enquiryCalledTimestamp": null,
  "reviews": null,
  "keyFeatures": [],
  "enhancedListing": false,
  "propertyImages": {
    "images": [
      {
        "srcUrl": "https://media.rightmove.co.uk:443/dir/crop/10:9-16:9/257k/256541/159676043/256541_ARU-778231_IMG_00_0000_max_476x317.jpeg",
        "url": "257k/256541/159676043/256541_ARU-778231_IMG_00_0000.jpeg",
        "caption": null
      },
      {
        "srcUrl": "https://media.rightmove.co.uk:443/dir/crop/10:9-16:9/257k/256541/159676043/256541_ARU-778231_IMG_01_0000_max_476x317.jpeg",
        "url": "257k/256541/159676043/256541_ARU-778231_IMG_01_0000.jpeg",
        "caption": null
      },
      {
        "srcUrl": "https://media.rightmove.co.uk:443/dir/crop/10:9-16:9/257k/256541/159676043/256541_ARU-778231_IMG_02_0000_max_476x317.jpeg",
        "url": "257k/256541/159676043/256541_ARU-778231_IMG_02_0000.jpeg",
        "caption": null
      },
      {
        "srcUrl": "https://media.rightmove.co.uk:443/dir/crop/10:9-16:9/257k/256541/159676043/256541_ARU-778231_IMG_03_0000_max_476x317.jpeg",
        "url": "257k/256541/159676043/256541_ARU-778231_IMG_03_0000.jpeg",
        "caption": null
      },
      {
        "srcUrl": "https://media.rightmove.co.uk:443/dir/crop/10:9-16:9/257k/256541/159676043/256541_ARU-778231_IMG_04_0000_max_476x317.jpeg",
        "url": "257k/256541/159676043/256541_ARU-778231_IMG_04_0000.jpeg",
        "caption": null
      },
      {
        "srcUrl": "https://media.rightmove.co.uk:443/dir/crop/10:9-16:9/257k/256541/159676043/256541_ARU-778231_IMG_05_0000_max_476x317.jpeg",
        "url": "257k/256541/159676043/256541_ARU-778231_IMG_05_0000.jpeg",
        "caption": null
      },
      {
        "srcUrl": "https://media.rightmove.co.uk:443/dir/crop/10:9-16:9/257k/256541/159676043/256541_ARU-778231_IMG_06_0000_max_476x317.jpeg",
        "url": "257k/256541/159676043/256541_ARU-778231_IMG_06_0000.jpeg",
        "caption": null
      },
      {
        "srcUrl": "https://media.rightmove.co.uk:443/dir/crop/10:9-16:9/257k/256541/159676043/256541_ARU-778231_IMG_07_0000_max_476x317.jpeg",
        "url": "257k/256541/159676043/256541_ARU-778231_IMG_07_0000.jpeg",
        "caption": null
      },
      {
        "srcUrl": "https://media.rightmove.co.uk:443/dir/crop/10:9-16:9/257k/256541/159676043/256541_ARU-778231_IMG_08_0000_max_476x317.jpeg",
        "url": "257k/256541/159676043/256541_ARU-778231_IMG_08_0000.jpeg",
        "caption": null
      },
      {
        "srcUrl": "https://media.rightmove.co.uk:443/dir/crop/10:9-16:9/257k/256541/159676043/256541_ARU-778231_IMG_09_0000_max_476x317.jpeg",
        "url": "257k/256541/159676043/256541_ARU-778231_IMG_09_0000.jpeg",
        "caption": null
      },
      {
        "srcUrl": "https://media.rightmove.co.uk:443/dir/crop/10:9-16:9/257k/256541/159676043/256541_ARU-778231_IMG_10_0000_max_476x317.jpeg",
        "url": "257k/256541/159676043/256541_ARU-778231_IMG_10_0000.jpeg",
        "caption": null
      },
      {
        "srcUrl": "https://media.rightmove.co.uk:443/dir/crop/10:9-16:9/257k/256541/159676043/256541_ARU-778231_IMG_11_0000_max_476x317.jpeg",
        "url": "257k/256541/159676043/256541_ARU-778231_IMG_11_0000.jpeg",
        "caption": null
      }
    ],
    "mainImageSrc": "https://media.rightmove.co.uk:443/dir/crop/10:9-16:9/257k/256541/159676043/256541_ARU-778231_IMG_00_0000_max_476x317.jpeg",
    "mainMapImageSrc": "https://media.rightmove.co.uk:443/dir/crop/10:9-16:9/257k/256541/159676043/256541_ARU-778231_IMG_00_0000_max_296x197.jpeg"
  },
  "formattedBranchName": " by Woodfell, London",
  "addedOrReduced": "Reduced on 06/10/2025",
  "formattedDistance": "",
  "heading": "",
  "propertyTypeFullDescription": "2 bedroom flat",
  "displayStatus": "",
  "isRecent": false,
  "hasBrandPlus": true
}