{
  "source": "rightmove",
  "scraped_at": "2025-11-06T22:30:47.952169+00:00",
  "postcode": "N19 3UZ",
  "id": 168964817,
  "bedrooms": 3,
  "bathrooms": 3,
  "numberOfImages": 8,
  "numberOfFloorplans": 0,
  "numberOfVirtualTours": 0,
  "summary": "3-bed, 3-bath conversion on Cardinal Way, Archway. Features spacious reception, modern shower, garden, gas central heating, washing machine, and pets allowed. Council Tax Band D. No parking or special accessibility.",
  "displayAddress": "Cardinal Way,",
  "countryCode": "GB",
  "location": {
    "latitude": 51.57014,
    "longitude": -0.13184
  },
  "images": [
    {
      "srcUrl": "https://media.rightmove.co.uk:443/dir/crop/10:9-16:9/288k/287924/168964817/287924_1167_IMG_00_0000_max_476x317.jpeg",
      "url": "288k/287924/168964817/287924_1167_IMG_00_0000.jpeg",
      "caption": null
    },
    {
      "srcUrl": "https://media.rightmove.co.uk:443/dir/crop/10:9-16:9/288k/287924/168964817/287924_1167_IMG_01_0000_max_476x317.jpeg",
      "url": "288k/287924/168964817/287924_1167_IMG_01_0000.jpeg",
      "caption": null
    },
    {
      "srcUrl": "https://media.rightmove.co.uk:443/dir/crop/10:9-16:9/288k/287924/168964817/287924_1167_IMG_02_0000_max_476x317.jpeg",
      "url": "288k/287924/168964817/287924_1167_IMG_02_0000.jpeg",
      "caption": null
    },
    {
      "srcUrl": "https://media.rightmove.co.uk:443/dir/crop/10:9-16:9/288k/287924/168964817/287924_1167_IMG_03_0000_max_476x317.jpeg",
      "url": "288k/287924/168964817/287924_1167_IMG_03_0000.jpeg",
      "caption": null
    },
    {
      "srcUrl": "https://media.rightmove.co.uk:443/dir/crop/10:9-16:9/288k/287924/168964817/287924_1167_IMG_04_0000_max_476x317.jpeg",
      "url": "288k/287924/168964817/287924_1167_IMG_04_0000.jpeg",
      "caption": null
    },
    {
      "srcUrl": "https://media.rightmove.co.uk:443/dir/crop/10:9-16:9/288k/287924/168964817/287924_1167_IMG_05_0000_max_476x317.jpeg",
      "url": "288k/287924/168964817/287924_1167_IMG_05_0000.jpeg",
      "caption": null
    },
    {
      "srcUrl": "https://media.rightmove.co.uk:443/dir/crop/10:9-16:9/288k/287924/168964817/287924_1167_IMG_06_0000_max_476x317.jpeg",
      "url": "288k/287924/168964817/287924_1167_IMG_06_0000.jpeg",
      "caption": null
    },
    {
      "srcUrl": "https://media.rightmove.co.uk:443/dir/crop/10:9-16:9/288k/287924/168964817/287924_1167_IMG_07_0000_max_476x317.jpeg",
      "url": "288k/287924/168964817/287924_1167_IMG_07_0000.jpeg",
      "caption": null
    }
  ],
  "propertySubType": "Flat",
  "tenure": {
    "tenureType": null
  },
  "letAvailableDate": "2025-11-14T00:00:00Z",
  "listingUpdate": {
    "listingUpdateReason": "new",
    "listingUpdateDate": "2025-11-04T11:54:03Z"
  },
  "price": {
    "amount": 3000,
    "frequency": "monthly",
    "currencyCode": "GBP",
    "displayPrices": [
      {
        "displayPrice": "\u00a33,000 pcm",
        "displayPriceQualifier": ""
      },
      {
        "displayPrice": "\u00a3692 pw",
        "displayPriceQualifier": ""
      }
    ]
  },
  "premiumListing": false,
  "featuredProperty": false,
  "customer": {
    "branchId": 287924,
    "brandPlusLogoURI": "/288k/287924/branch_rmchoice_logo_287924_0000.jpeg",
    "contactTelephone": "020 3929 2677",
    "branchDisplayName": "Northview Residential, London",
    "branchName": "London",
    "brandTradingName": "Northview Residential",
    "branchLandingPageUrl": "/estate-agents/agent/Northview-Residential/London-287924.html",
    "development": false,
    "mediaServerUrl": "https://media.rightmove.co.uk:443",
    "showReducedProperties": true,
    "hasBrandPlus": true,
    "commercial": false,
    "showOnMap": true,
    "enhancedListing": false,
    "developmentContent": null,
    "buildToRent": false,
    "buildToRentBenefits": [],
    "updateDate": "2025-10-06T23:41:27Z",
    "brandPlusLogoUrl": "https://media.rightmove.co.uk:443/288k/287924/branch_rmchoice_logo_287924_0000.jpeg",
    "primaryBrandColour": null
  },
  "distance": null,
  "transactionType": "rent",
  "productLabel": {
    "productLabelText": null,
    "spotlightLabel": false
  },
  "commercial": false,
  "development": false,
  "residential": true,
  "students": false,
  "auction": false,
  "feesApply": true,
  "feesApplyText": "Permitted Payments \n\nRent - Calculated as Rent Per Week X 52 Weeks / 12 months\n\nRefundable Tenancy Deposit - Equivalent to Five weeks rent when total rent is under \u00a350,000. Six weeks rent when total rent is over \u00a350,000. \n\nRefundable Holding Deposit - Equivalent 1 weeks rent. \n\nPayments to Change the Tenancy - \u00a350, if agreed by the landlord. \n\nPayments Associated with Early Termination of the Tenancy - \u00a3300 per tenant, if agreed by the landlord. \n\nFee for Late Payment - Fixed penalty charges for late payment of rent and/or fees imposed for chasing up late rent are prohibited, for example: \n\n  Late payment of rent that has been outstanding for 14 days or more will be charged at 3%+ Bank of England's base rate for each day that the payment is outstanding. \n\n  Should it be necessary to send a letter with regards to late payment of rent, these are chargeable to the tenant at a rate of \u00a327.50. Personal visits are charged at \u00a390.\n\nFee For Replacement of a Lost Key/Security Device - \u00a336\n\n**All prices are inclusive of VAT**\n",
  "displaySize": "",
  "showOnMap": true,
  "propertyUrl": "/properties/168964817#/?channel=RES_LET",
  "contactUrl": "/property-to-rent/contactBranch.html?propertyId=168964817",
  "staticMapUrl": null,
  "channel": "RENT",
  "firstVisibleDate": "2025-11-04T11:48:03Z",
  "keywords": [],
  "tags": [],
  "keywordMatchType": "no_keyword",
  "saved": false,
  "hidden": false,
  "onlineViewingsAvailable": false,
  "lozengeModel": {
    "matchingLozenges": []
  },
  "streetView": {
    "showStreetView": true
  },
  "enquiredTimestamp": null,
  "updateDate": "2025-11-04T15:00:28Z",
  "enquiryAddedTimestamp": null,
  "enquiryCalledTimestamp": null,
  "reviews": null,
  "enhancedListing": false,
  "propertyImages": {
    "images": [
      {
        "srcUrl": "https://media.rightmove.co.uk:443/dir/crop/10:9-16:9/288k/287924/168964817/287924_1167_IMG_00_0000_max_476x317.jpeg",
        "url": "288k/287924/168964817/287924_1167_IMG_00_0000.jpeg",
        "caption": null
      },
      {
        "srcUrl": "https://media.rightmove.co.uk:443/dir/crop/10:9-16:9/288k/287924/168964817/287924_1167_IMG_01_0000_max_476x317.jpeg",
        "url": "288k/287924/168964817/287924_1167_IMG_01_0000.jpeg",
        "caption": null
      },
      {
        "srcUrl": "https://media.rightmove.co.uk:443/dir/crop/10:9-16:9/288k/287924/168964817/287924_1167_IMG_02_0000_max_476x317.jpeg",
        "url": "288k/287924/168964817/287924_1167_IMG_02_0000.jpeg",
        "caption": null
      },
      {
        "srcUrl": "https://media.rightmove.co.uk:443/dir/crop/10:9-16:9/288k/287924/168964817/287924_1167_IMG_03_0000_max_476x317.jpeg",
        "url": "288k/287924/168964817/287924_1167_IMG_03_0000.jpeg",
        "caption": null
      },
      {
        "srcUrl": "https://media.rightmove.co.uk:443/dir/crop/10:9-16:9/288k/287924/168964817/287924_1167_IMG_04_0000_max_476x317.jpeg",
        "url": "288k/287924/168964817/287924_1167_IMG_04_0000.jpeg",
        "caption": null
      },
      {
        "srcUrl": "https://media.rightmove.co.uk:443/dir/crop/10:9-16:9/288k/287924/168964817/287924_1167_IMG_05_0000_max_476x317.jpeg",
        "url": "288k/287924/168964817/287924_1167_IMG_05_0000.jpeg",
        "caption": null
      },
      {
        "srcUrl": "https://media.rightmove.co.uk:443/dir/crop/10:9-16:9/288k/287924/168964817/287924_1167_IMG_06_0000_max_476x317.jpeg",
        "url": "288k/287924/168964817/287924_1167_IMG_06_0000.jpeg",
        "caption": null
      },
      {
        "srcUrl": "https://media.rightmove.co.uk:443/dir/crop/10:9-16:9/288k/287924/168964817/287924_1167_IMG_07_0000_max_476x317.jpeg",
        "url": "288k/287924/168964817/287924_1167_IMG_07_0000.jpeg",
        "caption": null
      }
    ],
    "mainImageSrc": "https://media.rightmove.co.uk:443/dir/crop/10:9-16:9/288k/287924/168964817/287924_1167_IMG_00_0000_max_476x317.jpeg",
    "mainMapImageSrc": "https://media.rightmove.co.uk:443/dir/crop/10:9-16:9/288k/287924/168964817/287924_1167_IMG_00_0000_max_296x197.jpeg"
  },
  "formattedBranchName": " by Northview Residential, London",
  "addedOrReduced": "Added on 04/11/2025",
  "formattedDistance": "",
  "heading": "",
  "propertyTypeFullDescription": "3 bedroom flat",
  "displayStatus": "",
  "isRecent": false,
  "hasBrandPlus": true
}