{
  "source": "rightmove",
  "scraped_at": "2026-07-23T23:23:23.362673+00:00",
  "postcode": "N1 9FS",
  "id": 91130481,
  "bedrooms": 0,
  "bathrooms": null,
  "numberOfImages": 3,
  "numberOfFloorplans": 0,
  "numberOfVirtualTours": 0,
  "summary": "Stylish newly refurbished studio apartment in the heart of King's Cross, finished to a high standard with contemporary interiors and a smart, space-efficient layout. Ideally located within walking distance of King's Cross St Pancras, with excellent transport links, caf\u00e9s, restaur...",
  "displayAddress": "A501, London, N1",
  "countryCode": "GB",
  "location": {
    "latitude": 51.527322,
    "longitude": -0.130632
  },
  "images": [
    {
      "srcUrl": "https://media.rightmove.co.uk:443/dir/crop/10:9-16:9/property-photo/f546db3a7/91130481/f546db3a7d76b2c5eefa8511bbfc5e4c_max_476x317.jpeg",
      "url": "property-photo/f546db3a7/91130481/f546db3a7d76b2c5eefa8511bbfc5e4c.jpeg",
      "caption": "Picture No. 03"
    },
    {
      "srcUrl": "https://media.rightmove.co.uk:443/dir/crop/10:9-16:9/property-photo/b26004a67/91130481/b26004a67be9e75908d35c0b655a79c9_max_476x317.jpeg",
      "url": "property-photo/b26004a67/91130481/b26004a67be9e75908d35c0b655a79c9.jpeg",
      "caption": "Picture No. 02"
    },
    {
      "srcUrl": "https://media.rightmove.co.uk:443/dir/crop/10:9-16:9/property-photo/0267cfa23/91130481/0267cfa23379fdbbbb8f9b0a16c49845_max_476x317.jpeg",
      "url": "property-photo/0267cfa23/91130481/0267cfa23379fdbbbb8f9b0a16c49845.jpeg",
      "caption": "Picture No. 01"
    }
  ],
  "propertySubType": "Studio",
  "tenure": {
    "tenureType": null
  },
  "letAvailableDate": "2026-08-10T00:00:00Z",
  "listingUpdate": {
    "listingUpdateReason": "new",
    "listingUpdateDate": "2026-07-21T09:03:42Z"
  },
  "price": {
    "amount": 2250,
    "frequency": "monthly",
    "currencyCode": "GBP",
    "displayPrices": [
      {
        "displayPrice": "\u00a32,250 pcm",
        "displayPriceQualifier": ""
      },
      {
        "displayPrice": "\u00a3519 pw",
        "displayPriceQualifier": ""
      }
    ]
  },
  "premiumListing": false,
  "featuredProperty": false,
  "commercialSearchProminenceSelected": false,
  "customer": {
    "branchId": 222842,
    "brandPlusLogoURI": "/partner-logo/24059822-PRODUCTS_LOGO-1766059131.png",
    "contactTelephone": "01483 967984",
    "branchDisplayName": "The Chant Group, Bank",
    "branchName": "Bank",
    "brandTradingName": "The Chant Group",
    "branchLandingPageUrl": "/estate-agents/agent/The-Chant-Group/Bank-222842.html",
    "development": false,
    "mediaServerUrl": "https://media.rightmove.co.uk:443",
    "showReducedProperties": true,
    "hasBrandPlus": true,
    "commercial": false,
    "showOnMap": true,
    "enhancedListing": false,
    "developmentContent": null,
    "buildToRent": false,
    "buildToRentBenefits": [],
    "updateDate": "2026-03-26T17:40:40Z",
    "brandPlusLogoUrl": "https://media.rightmove.co.uk:443/partner-logo/24059822-PRODUCTS_LOGO-1766059131.png",
    "primaryBrandColour": "#e4dfd2"
  },
  "distance": null,
  "transactionType": "rent",
  "productLabel": {
    "productLabelText": null,
    "spotlightLabel": false
  },
  "commercial": false,
  "development": false,
  "residential": true,
  "students": false,
  "auction": false,
  "feesApply": true,
  "feesApplyText": null,
  "displaySize": "",
  "showOnMap": true,
  "propertyUrl": "/properties/91130481#/?channel=RES_LET",
  "contactUrl": "/property-to-rent/contactBranch.html?propertyId=91130481",
  "staticMapUrl": null,
  "channel": "RENT",
  "firstVisibleDate": "2026-07-21T08:58:25Z",
  "keywords": [],
  "tags": [],
  "keywordMatchType": "no_keyword",
  "saved": false,
  "hidden": false,
  "onlineViewingsAvailable": false,
  "lozengeModel": {
    "matchingLozenges": []
  },
  "streetView": {
    "showStreetView": true
  },
  "enquiredTimestamp": null,
  "updateDate": "2026-07-23T06:30:54Z",
  "enquiryAddedTimestamp": null,
  "enquiryCalledTimestamp": null,
  "reviews": null,
  "keyFeatures": [],
  "enhancedListing": false,
  "propertyImages": {
    "images": [
      {
        "srcUrl": "https://media.rightmove.co.uk:443/dir/crop/10:9-16:9/property-photo/f546db3a7/91130481/f546db3a7d76b2c5eefa8511bbfc5e4c_max_476x317.jpeg",
        "url": "property-photo/f546db3a7/91130481/f546db3a7d76b2c5eefa8511bbfc5e4c.jpeg",
        "caption": "Picture No. 03"
      },
      {
        "srcUrl": "https://media.rightmove.co.uk:443/dir/crop/10:9-16:9/property-photo/b26004a67/91130481/b26004a67be9e75908d35c0b655a79c9_max_476x317.jpeg",
        "url": "property-photo/b26004a67/91130481/b26004a67be9e75908d35c0b655a79c9.jpeg",
        "caption": "Picture No. 02"
      },
      {
        "srcUrl": "https://media.rightmove.co.uk:443/dir/crop/10:9-16:9/property-photo/0267cfa23/91130481/0267cfa23379fdbbbb8f9b0a16c49845_max_476x317.jpeg",
        "url": "property-photo/0267cfa23/91130481/0267cfa23379fdbbbb8f9b0a16c49845.jpeg",
        "caption": "Picture No. 01"
      }
    ],
    "mainImageSrc": "https://media.rightmove.co.uk:443/dir/crop/10:9-16:9/property-photo/f546db3a7/91130481/f546db3a7d76b2c5eefa8511bbfc5e4c_max_476x317.jpeg",
    "mainMapImageSrc": "https://media.rightmove.co.uk:443/dir/crop/10:9-16:9/property-photo/f546db3a7/91130481/f546db3a7d76b2c5eefa8511bbfc5e4c_max_296x197.jpeg"
  },
  "formattedBranchName": " by The Chant Group, Bank",
  "addedOrReduced": "Added on 21/07/2026",
  "formattedDistance": "",
  "heading": "",
  "propertyTypeFullDescription": "Studio flat",
  "displayStatus": "",
  "isRecent": false,
  "hasBrandPlus": true
}