{
  "source": "rightmove",
  "scraped_at": "2026-05-17T22:15:20.991412+00:00",
  "postcode": "N1 4QR",
  "id": 123266273,
  "bedrooms": 1,
  "bathrooms": 1,
  "numberOfImages": 5,
  "numberOfFloorplans": 1,
  "numberOfVirtualTours": 0,
  "summary": "Situated on the renowned Newington Green Road on the cusp of Highbury & Islington and Newington Green is this one double bedroom flat found in the midst of it all. The flat is positioned on the first floor of a charming building and within close proximity is Canonbury and Highbury & Islin...",
  "displayAddress": "Newington Green Road, London, N1",
  "countryCode": "GB",
  "location": {
    "latitude": 51.548695,
    "longitude": -0.087666
  },
  "images": [
    {
      "srcUrl": "https://media.rightmove.co.uk:443/dir/crop/10:9-16:9/property-photo/868b7518d/123266273/868b7518d538af671e0e5a2d23b02117_max_476x317.jpeg",
      "url": "property-photo/868b7518d/123266273/868b7518d538af671e0e5a2d23b02117.jpeg",
      "caption": "Exterior"
    },
    {
      "srcUrl": "https://media.rightmove.co.uk:443/dir/crop/10:9-16:9/property-photo/847506a63/123266273/847506a63677d06ee27cff026050782e_max_476x317.jpeg",
      "url": "property-photo/847506a63/123266273/847506a63677d06ee27cff026050782e.jpeg",
      "caption": "Bedroom"
    },
    {
      "srcUrl": "https://media.rightmove.co.uk:443/dir/crop/10:9-16:9/property-photo/e3c4eb9f1/123266273/e3c4eb9f150c053f8410abecf047505a_max_476x317.jpeg",
      "url": "property-photo/e3c4eb9f1/123266273/e3c4eb9f150c053f8410abecf047505a.jpeg",
      "caption": "Reception/Dining"
    },
    {
      "srcUrl": "https://media.rightmove.co.uk:443/dir/crop/10:9-16:9/property-photo/530e05c95/123266273/530e05c95518110a7230ea2dd2e084da_max_476x317.jpeg",
      "url": "property-photo/530e05c95/123266273/530e05c95518110a7230ea2dd2e084da.jpeg",
      "caption": "Reception/Dining"
    },
    {
      "srcUrl": "https://media.rightmove.co.uk:443/dir/crop/10:9-16:9/property-photo/14eb4fdf9/123266273/14eb4fdf9b4a4064396b616ce2258a7f_max_476x317.jpeg",
      "url": "property-photo/14eb4fdf9/123266273/14eb4fdf9b4a4064396b616ce2258a7f.jpeg",
      "caption": "Bathroom"
    }
  ],
  "propertySubType": "Apartment",
  "tenure": {
    "tenureType": null
  },
  "letAvailableDate": "2026-06-10T00:00:00Z",
  "listingUpdate": {
    "listingUpdateReason": "new",
    "listingUpdateDate": "2026-05-15T12:24:48Z"
  },
  "price": {
    "amount": 1400,
    "frequency": "monthly",
    "currencyCode": "GBP",
    "displayPrices": [
      {
        "displayPrice": "\u00a31,400 pcm",
        "displayPriceQualifier": ""
      },
      {
        "displayPrice": "\u00a3323 pw",
        "displayPriceQualifier": ""
      }
    ]
  },
  "premiumListing": false,
  "featuredProperty": false,
  "commercialSearchProminenceSelected": false,
  "customer": {
    "branchId": 191252,
    "brandPlusLogoURI": "/partner-logo/19965338-PRODUCTS_LOGO-1766065227.jpeg",
    "contactTelephone": "020 3907 9804",
    "branchDisplayName": "Property Inc, Harringay",
    "branchName": "Harringay",
    "brandTradingName": "Property Inc",
    "branchLandingPageUrl": "/estate-agents/agent/Property-Inc/Harringay-191252.html",
    "development": false,
    "mediaServerUrl": "https://media.rightmove.co.uk:443",
    "showReducedProperties": true,
    "hasBrandPlus": true,
    "commercial": false,
    "showOnMap": true,
    "enhancedListing": false,
    "developmentContent": null,
    "buildToRent": false,
    "buildToRentBenefits": [],
    "updateDate": "2026-03-16T09:23:30Z",
    "brandPlusLogoUrl": "https://media.rightmove.co.uk:443/partner-logo/19965338-PRODUCTS_LOGO-1766065227.jpeg",
    "primaryBrandColour": null
  },
  "distance": null,
  "transactionType": "rent",
  "productLabel": {
    "productLabelText": null,
    "spotlightLabel": false
  },
  "commercial": false,
  "development": false,
  "residential": true,
  "students": false,
  "auction": false,
  "feesApply": true,
  "feesApplyText": null,
  "displaySize": "",
  "showOnMap": true,
  "propertyUrl": "/properties/123266273#/?channel=RES_LET",
  "contactUrl": "/property-to-rent/contactBranch.html?propertyId=123266273",
  "staticMapUrl": null,
  "channel": "RENT",
  "firstVisibleDate": "2022-05-11T19:47:24Z",
  "keywords": [],
  "tags": [],
  "keywordMatchType": "no_keyword",
  "saved": false,
  "hidden": false,
  "onlineViewingsAvailable": false,
  "lozengeModel": {
    "matchingLozenges": []
  },
  "streetView": {
    "showStreetView": true
  },
  "enquiredTimestamp": null,
  "updateDate": "2026-05-15T15:58:21Z",
  "enquiryAddedTimestamp": null,
  "enquiryCalledTimestamp": null,
  "reviews": null,
  "keyFeatures": [],
  "enhancedListing": false,
  "propertyImages": {
    "images": [
      {
        "srcUrl": "https://media.rightmove.co.uk:443/dir/crop/10:9-16:9/property-photo/868b7518d/123266273/868b7518d538af671e0e5a2d23b02117_max_476x317.jpeg",
        "url": "property-photo/868b7518d/123266273/868b7518d538af671e0e5a2d23b02117.jpeg",
        "caption": "Exterior"
      },
      {
        "srcUrl": "https://media.rightmove.co.uk:443/dir/crop/10:9-16:9/property-photo/847506a63/123266273/847506a63677d06ee27cff026050782e_max_476x317.jpeg",
        "url": "property-photo/847506a63/123266273/847506a63677d06ee27cff026050782e.jpeg",
        "caption": "Bedroom"
      },
      {
        "srcUrl": "https://media.rightmove.co.uk:443/dir/crop/10:9-16:9/property-photo/e3c4eb9f1/123266273/e3c4eb9f150c053f8410abecf047505a_max_476x317.jpeg",
        "url": "property-photo/e3c4eb9f1/123266273/e3c4eb9f150c053f8410abecf047505a.jpeg",
        "caption": "Reception/Dining"
      },
      {
        "srcUrl": "https://media.rightmove.co.uk:443/dir/crop/10:9-16:9/property-photo/530e05c95/123266273/530e05c95518110a7230ea2dd2e084da_max_476x317.jpeg",
        "url": "property-photo/530e05c95/123266273/530e05c95518110a7230ea2dd2e084da.jpeg",
        "caption": "Reception/Dining"
      },
      {
        "srcUrl": "https://media.rightmove.co.uk:443/dir/crop/10:9-16:9/property-photo/14eb4fdf9/123266273/14eb4fdf9b4a4064396b616ce2258a7f_max_476x317.jpeg",
        "url": "property-photo/14eb4fdf9/123266273/14eb4fdf9b4a4064396b616ce2258a7f.jpeg",
        "caption": "Bathroom"
      }
    ],
    "mainImageSrc": "https://media.rightmove.co.uk:443/dir/crop/10:9-16:9/property-photo/868b7518d/123266273/868b7518d538af671e0e5a2d23b02117_max_476x317.jpeg",
    "mainMapImageSrc": "https://media.rightmove.co.uk:443/dir/crop/10:9-16:9/property-photo/868b7518d/123266273/868b7518d538af671e0e5a2d23b02117_max_296x197.jpeg"
  },
  "formattedBranchName": " by Property Inc, Harringay",
  "addedOrReduced": "Added on 15/05/2026",
  "formattedDistance": "",
  "heading": "",
  "propertyTypeFullDescription": "1 bedroom apartment",
  "displayStatus": "",
  "isRecent": false,
  "hasBrandPlus": true
}