{
  "source": "rightmove",
  "scraped_at": "2026-01-22T20:18:36.817515+00:00",
  "postcode": "EC1M 7AH",
  "id": 171316796,
  "bedrooms": 1,
  "bathrooms": 1,
  "numberOfImages": 6,
  "numberOfFloorplans": 0,
  "numberOfVirtualTours": 0,
  "summary": "A newly refurbished 1 bedroom apartment located within 1 minute's walk from Barbican tube station.",
  "displayAddress": "Goswell Road, London, EC1M",
  "countryCode": "GB",
  "location": {
    "latitude": 51.521679,
    "longitude": -0.097588
  },
  "images": [
    {
      "srcUrl": "https://media.rightmove.co.uk:443/dir/crop/10:9-16:9/property-photo/326710eeb/171316796/326710eeb2d5ee07f7252de72b74625e_max_476x317.jpeg",
      "url": "property-photo/326710eeb/171316796/326710eeb2d5ee07f7252de72b74625e.jpeg",
      "caption": null
    },
    {
      "srcUrl": "https://media.rightmove.co.uk:443/dir/crop/10:9-16:9/property-photo/d38b8f900/171316796/d38b8f900e424a23c68a8241ca3209c9_max_476x317.jpeg",
      "url": "property-photo/d38b8f900/171316796/d38b8f900e424a23c68a8241ca3209c9.jpeg",
      "caption": null
    },
    {
      "srcUrl": "https://media.rightmove.co.uk:443/dir/crop/10:9-16:9/property-photo/e7fd972c4/171316796/e7fd972c4b0aee7e3f1f551c586129d3_max_476x317.jpeg",
      "url": "property-photo/e7fd972c4/171316796/e7fd972c4b0aee7e3f1f551c586129d3.jpeg",
      "caption": null
    },
    {
      "srcUrl": "https://media.rightmove.co.uk:443/dir/crop/10:9-16:9/property-photo/d6ac94641/171316796/d6ac94641cc74a7f72454d42a79eeda1_max_476x317.jpeg",
      "url": "property-photo/d6ac94641/171316796/d6ac94641cc74a7f72454d42a79eeda1.jpeg",
      "caption": null
    },
    {
      "srcUrl": "https://media.rightmove.co.uk:443/dir/crop/10:9-16:9/property-photo/4d9920d93/171316796/4d9920d938af8926751a5b3c897b7601_max_476x317.jpeg",
      "url": "property-photo/4d9920d93/171316796/4d9920d938af8926751a5b3c897b7601.jpeg",
      "caption": null
    },
    {
      "srcUrl": "https://media.rightmove.co.uk:443/dir/crop/10:9-16:9/property-photo/97e59a67e/171316796/97e59a67e1ec108c8fd3d156dd71b8ae_max_476x317.jpeg",
      "url": "property-photo/97e59a67e/171316796/97e59a67e1ec108c8fd3d156dd71b8ae.jpeg",
      "caption": null
    }
  ],
  "propertySubType": "Flat",
  "tenure": {
    "tenureType": null
  },
  "letAvailableDate": "2026-02-18T00:00:00Z",
  "listingUpdate": {
    "listingUpdateReason": "new",
    "listingUpdateDate": "2025-11-28T16:57:07Z"
  },
  "price": {
    "amount": 1800,
    "frequency": "monthly",
    "currencyCode": "GBP",
    "displayPrices": [
      {
        "displayPrice": "\u00a31,800 pcm",
        "displayPriceQualifier": ""
      },
      {
        "displayPrice": "\u00a3415 pw",
        "displayPriceQualifier": ""
      }
    ]
  },
  "premiumListing": false,
  "featuredProperty": false,
  "commercialSearchProminenceSelected": false,
  "customer": {
    "branchId": 295751,
    "brandPlusLogoURI": "/296k/295751/branch_rmchoice_logo_295751_0000.jpeg",
    "contactTelephone": "020 7729 3344",
    "branchDisplayName": "City & Urban, Shoreditch",
    "branchName": "Shoreditch",
    "brandTradingName": "City & Urban",
    "branchLandingPageUrl": "/estate-agents/agent/City-and-Urban/Shoreditch-295751.html",
    "development": false,
    "mediaServerUrl": "https://media.rightmove.co.uk:443",
    "showReducedProperties": true,
    "hasBrandPlus": true,
    "commercial": false,
    "showOnMap": true,
    "enhancedListing": false,
    "developmentContent": null,
    "buildToRent": false,
    "buildToRentBenefits": [],
    "updateDate": "2025-10-21T15:07:17Z",
    "brandPlusLogoUrl": "https://media.rightmove.co.uk:443/296k/295751/branch_rmchoice_logo_295751_0000.jpeg",
    "primaryBrandColour": null
  },
  "distance": null,
  "transactionType": "rent",
  "productLabel": {
    "productLabelText": null,
    "spotlightLabel": false
  },
  "commercial": false,
  "development": false,
  "residential": true,
  "students": false,
  "auction": false,
  "feesApply": true,
  "feesApplyText": "Permitted Payments\n\nBefore the tenancy starts (payable to City & Urban Shoreditch  the Agent )\n\nHolding Deposit: 1 week s rent\nDeposit: 5 weeks  rent\n\nDuring the tenancy (payable to the Agent)\n\nPayment of up to \u00a350.00 if you want to change the tenancy agreement.\nPayment of interest for the late payment of rent at a rate of 3% above the Base Rate.\nPayment of up to \u00a350.00 for the reasonably incurred costs for the loss of keys/security devices.\nPayment of any unpaid rent or other reasonable costs associated with your early termination of the tenancy.\n\nTenant Protection\nCity & Urban Shoreditch is a member of The Property Ombudsmen, which is a redress scheme.\nMembership Number: D/2745/3.\n\nCity & Urban Shoreditch is a member of Propertymark Client Money Protection which is a client\nmoney protection scheme.\nMembership Number: C0134660",
  "displaySize": "",
  "showOnMap": true,
  "propertyUrl": "/properties/171316796#/?channel=RES_LET",
  "contactUrl": "/property-to-rent/contactBranch.html?propertyId=171316796",
  "staticMapUrl": null,
  "channel": "RENT",
  "firstVisibleDate": "2026-01-22T15:56:53Z",
  "keywords": [],
  "tags": [],
  "keywordMatchType": "no_keyword",
  "saved": false,
  "hidden": false,
  "onlineViewingsAvailable": false,
  "lozengeModel": {
    "matchingLozenges": []
  },
  "streetView": {
    "showStreetView": true
  },
  "enquiredTimestamp": null,
  "updateDate": "2026-01-22T16:02:06Z",
  "enquiryAddedTimestamp": null,
  "enquiryCalledTimestamp": null,
  "reviews": null,
  "keyFeatures": [
    {
      "order": 1,
      "description": "Newly refurbished",
      "htmlDescription": "Newly refurbished"
    },
    {
      "order": 2,
      "description": "Available unfurnished from 18th February",
      "htmlDescription": "Available unfurnished from 18th February"
    }
  ],
  "enhancedListing": false,
  "propertyImages": {
    "images": [
      {
        "srcUrl": "https://media.rightmove.co.uk:443/dir/crop/10:9-16:9/property-photo/326710eeb/171316796/326710eeb2d5ee07f7252de72b74625e_max_476x317.jpeg",
        "url": "property-photo/326710eeb/171316796/326710eeb2d5ee07f7252de72b74625e.jpeg",
        "caption": null
      },
      {
        "srcUrl": "https://media.rightmove.co.uk:443/dir/crop/10:9-16:9/property-photo/d38b8f900/171316796/d38b8f900e424a23c68a8241ca3209c9_max_476x317.jpeg",
        "url": "property-photo/d38b8f900/171316796/d38b8f900e424a23c68a8241ca3209c9.jpeg",
        "caption": null
      },
      {
        "srcUrl": "https://media.rightmove.co.uk:443/dir/crop/10:9-16:9/property-photo/e7fd972c4/171316796/e7fd972c4b0aee7e3f1f551c586129d3_max_476x317.jpeg",
        "url": "property-photo/e7fd972c4/171316796/e7fd972c4b0aee7e3f1f551c586129d3.jpeg",
        "caption": null
      },
      {
        "srcUrl": "https://media.rightmove.co.uk:443/dir/crop/10:9-16:9/property-photo/d6ac94641/171316796/d6ac94641cc74a7f72454d42a79eeda1_max_476x317.jpeg",
        "url": "property-photo/d6ac94641/171316796/d6ac94641cc74a7f72454d42a79eeda1.jpeg",
        "caption": null
      },
      {
        "srcUrl": "https://media.rightmove.co.uk:443/dir/crop/10:9-16:9/property-photo/4d9920d93/171316796/4d9920d938af8926751a5b3c897b7601_max_476x317.jpeg",
        "url": "property-photo/4d9920d93/171316796/4d9920d938af8926751a5b3c897b7601.jpeg",
        "caption": null
      },
      {
        "srcUrl": "https://media.rightmove.co.uk:443/dir/crop/10:9-16:9/property-photo/97e59a67e/171316796/97e59a67e1ec108c8fd3d156dd71b8ae_max_476x317.jpeg",
        "url": "property-photo/97e59a67e/171316796/97e59a67e1ec108c8fd3d156dd71b8ae.jpeg",
        "caption": null
      }
    ],
    "mainImageSrc": "https://media.rightmove.co.uk:443/dir/crop/10:9-16:9/property-photo/326710eeb/171316796/326710eeb2d5ee07f7252de72b74625e_max_476x317.jpeg",
    "mainMapImageSrc": "https://media.rightmove.co.uk:443/dir/crop/10:9-16:9/property-photo/326710eeb/171316796/326710eeb2d5ee07f7252de72b74625e_max_296x197.jpeg"
  },
  "formattedBranchName": " by City & Urban, Shoreditch",
  "addedOrReduced": "Added on 28/11/2025",
  "formattedDistance": "",
  "heading": "",
  "propertyTypeFullDescription": "1 bedroom flat",
  "displayStatus": "",
  "isRecent": false,
  "hasBrandPlus": true
}